Metadata-Version: 2.1
Name: pipreqgen
Version: 0.0.1
Summary: Generates requirement.txt
Author: Muktadir
